{
  "001": {
    "title": "前端开发",
    "content": [
      {
        "id": "100",
        "name": "JavsScript中文网",
        "href": "https://www.javascriptcn.com/",
        "description": "JavsScript教程资源分享门户"
      },
      {
        "id": "101",
        "name": "Vue.js",
        "href": "https://cn.vuejs.org/",
        "description": "易学易用，性能出色，适用场景丰富的 Web 前端框架"
      },
      {
        "id": "102",
        "name": "Node.js中文网",
        "href": "https://nodejs.cn/",
        "description": "一个开源的、跨平台的 JavaScript 运行时环境"
      },
      {
        "id": "103",
        "name": "TypeScript中文网",
        "href": "https://www.tslang.cn/",
        "description": "一JavaScript 的超集"
      }
    ]
  }
}
